setup.cfg
setup.py
cooperhewitt/__init__.py
cooperhewitt.api.egg-info/PKG-INFO
cooperhewitt.api.egg-info/SOURCES.txt
cooperhewitt.api.egg-info/dependency_links.txt
cooperhewitt.api.egg-info/namespace_packages.txt
cooperhewitt.api.egg-info/requires.txt
cooperhewitt.api.egg-info/top_level.txt
cooperhewitt/api/__init__.py
cooperhewitt/api/client.py
cooperhewitt/api/request.py