Metadata-Version: 1.1
Name: cooperhewitt.api
Version: 0.4.3
Summary: Simple Python wrapper for Cooper-Hewitt API
Home-page: https://github.com/cooperhewitt/py-cooperhewitt-api
Author: Smithsonian Cooper-Hewitt National Design Museum
Author-email: UNKNOWN
License: BSD
Download-URL: https://github.com/cooperhewitt/py-cooperhewitt-api/releases/tag/v0.4.3
Platform: UNKNOWN
